ape_linea/__init__.py
ape_linea/ecosystem.py
ape_linea/py.typed
ape_linea/version.py
ape_linea-0.6.0a4.dist-info/LICENSE
ape_linea-0.6.0a4.dist-info/METADATA
ape_linea-0.6.0a4.dist-info/WHEEL
ape_linea-0.6.0a4.dist-info/top_level.txt
ape_linea-0.6.0a4.dist-info/RECORD
