Metadata-Version: 2.1
Name: ape-linea
Version: 0.6.0a4
Summary: ape-linea: Ape Ecosystem Plugin for Linea
Home-page: https://github.com/ApeWorX/ape-linea
Author: ApeWorX Ltd.
Author-email: admin@apeworx.io
License: Apache-2.0
Keywords: ethereum
Classifier: Development Status :: 5 - Production/Stable
Classifier: Intended Audience :: Developers
Classifier: License :: OSI Approved :: Apache Software License
Classifier: Natural Language :: English
Classifier: Operating System :: MacOS
Classifier: Operating System :: POSIX
Classifier: Programming Language :: Python :: 3
Classifier: Programming Language :: Python :: 3.8
Classifier: Programming Language :: Python :: 3.9
Classifier: Programming Language :: Python :: 3.10
Requires-Python: >=3.8,<4
License-File: LICENSE
Requires-Dist: eth-ape (<0.7,>=0.6.0)
Provides-Extra: dev
Requires-Dist: pytest (>=6.0) ; extra == 'dev'
Requires-Dist: pytest-mock ; extra == 'dev'
Requires-Dist: pytest-xdist ; extra == 'dev'
Requires-Dist: pytest-cov ; extra == 'dev'
Requires-Dist: hypothesis (<7.0,>=6.2.0) ; extra == 'dev'
Requires-Dist: black (>=22.12.0) ; extra == 'dev'
Requires-Dist: mypy (>=0.991) ; extra == 'dev'
Requires-Dist: flake8 (>=5.0.4) ; extra == 'dev'
Requires-Dist: isort (>=5.10.1) ; extra == 'dev'
Requires-Dist: types-setuptools ; extra == 'dev'
Requires-Dist: mdformat (>=0.7.16) ; extra == 'dev'
Requires-Dist: mdformat-gfm (>=0.3.5) ; extra == 'dev'
Requires-Dist: mdformat-frontmatter (>=0.4.1) ; extra == 'dev'
Requires-Dist: myst-parser (<0.18,>=0.17.0) ; extra == 'dev'
Requires-Dist: sphinx-click (<4.0,>=3.1.0) ; extra == 'dev'
Requires-Dist: Sphinx (<5.0,>=4.4.0) ; extra == 'dev'
Requires-Dist: sphinx-rtd-theme (<2,>=1.0.0) ; extra == 'dev'
Requires-Dist: sphinxcontrib-napoleon (>=0.7) ; extra == 'dev'
Requires-Dist: setuptools ; extra == 'dev'
Requires-Dist: setuptools-scm ; extra == 'dev'
Requires-Dist: wheel ; extra == 'dev'
Requires-Dist: twine ; extra == 'dev'
Requires-Dist: commitizen ; extra == 'dev'
Requires-Dist: pre-commit ; extra == 'dev'
Requires-Dist: pytest-watch ; extra == 'dev'
Requires-Dist: ipdb ; extra == 'dev'
Provides-Extra: doc
Requires-Dist: myst-parser (<0.18,>=0.17.0) ; extra == 'doc'
Requires-Dist: sphinx-click (<4.0,>=3.1.0) ; extra == 'doc'
Requires-Dist: Sphinx (<5.0,>=4.4.0) ; extra == 'doc'
Requires-Dist: sphinx-rtd-theme (<2,>=1.0.0) ; extra == 'doc'
Requires-Dist: sphinxcontrib-napoleon (>=0.7) ; extra == 'doc'
Provides-Extra: lint
Requires-Dist: black (>=22.12.0) ; extra == 'lint'
Requires-Dist: mypy (>=0.991) ; extra == 'lint'
Requires-Dist: flake8 (>=5.0.4) ; extra == 'lint'
Requires-Dist: isort (>=5.10.1) ; extra == 'lint'
Requires-Dist: types-setuptools ; extra == 'lint'
Requires-Dist: mdformat (>=0.7.16) ; extra == 'lint'
Requires-Dist: mdformat-gfm (>=0.3.5) ; extra == 'lint'
Requires-Dist: mdformat-frontmatter (>=0.4.1) ; extra == 'lint'
Provides-Extra: release
Requires-Dist: setuptools ; extra == 'release'
Requires-Dist: setuptools-scm ; extra == 'release'
Requires-Dist: wheel ; extra == 'release'
Requires-Dist: twine ; extra == 'release'
Provides-Extra: test
Requires-Dist: pytest (>=6.0) ; extra == 'test'
Requires-Dist: pytest-mock ; extra == 'test'
Requires-Dist: pytest-xdist ; extra == 'test'
Requires-Dist: pytest-cov ; extra == 'test'
Requires-Dist: hypothesis (<7.0,>=6.2.0) ; extra == 'test'
